<?xml version="1.0" encoding="UTF-8"?>
<list>
<item>
  <email>valerie.morgan@bitrex.name</email>
  <balance>$3,714.25</balance>
</item>
<item>
  <email>marianne.cummings@enthaze.ca</email>
  <balance>$3,549.00</balance>
</item>
<item>
  <email>hendrix.copeland@halap.tv</email>
  <balance>$1,881.32</balance>
</item>
<item>
  <email>theresa.melton@playce.net</email>
  <balance>$2,647.30</balance>
</item>
<item>
  <email>delores.montoya@kaggle.io</email>
  <balance>$2,983.79</balance>
</item>
<item>
  <email>bettie.doyle@sulfax.com</email>
  <balance>$3,125.53</balance>
</item>
<item>
  <email>diana.hatfield@isologix.co.uk</email>
  <balance>$2,777.52</balance>
</item>
<item>
  <email>andrews.rowe@moltonic.info</email>
  <balance>$2,729.50</balance>
</item>
<item>
  <email>vonda.haley@bleeko.us</email>
  <balance>$3,726.95</balance>
</item>
<item>
  <email>carroll.cole@norali.biz</email>
  <balance>$1,310.41</balance>
</item></list>
